AutoGenix_ETL/CsvLoader.py
AutoGenix_ETL/JSONLoader.py
AutoGenix_ETL/__init__.py
AutoGenix_ETL/determine_orient.py
tests/__init__.py
tests/test_CsvLoader.py
tests/test_JSONLoader.py
tests/test_determine_orient.py
autogenix_ETL_automation-0.1.0.dist-info/LICENSE
autogenix_ETL_automation-0.1.0.dist-info/METADATA
autogenix_ETL_automation-0.1.0.dist-info/WHEEL
autogenix_ETL_automation-0.1.0.dist-info/top_level.txt
autogenix_ETL_automation-0.1.0.dist-info/RECORD
