Metadata-Version: 2.2
Name: autogenix-ETL-automation
Version: 0.1.0
Summary: A package for automating ETL processes
Home-page: https://github.com/yourusername/autogenix-ETL-automation
Author: Rishikeswaran S
Author-email: rishikeswaran17@gmail.com
Classifier: Programming Language :: Python :: 3
Classifier: License :: OSI Approved :: MIT License
Classifier: Operating System :: OS Independent
Requires-Python: >=3.6
License-File: LICENSE
Requires-Dist: pandas
Dynamic: author
Dynamic: author-email
Dynamic: classifier
Dynamic: description
Dynamic: description-content-type
Dynamic: home-page
Dynamic: requires-dist
Dynamic: requires-python
Dynamic: summary
